odoo/addons/product_packaging_usability/README.rst
odoo/addons/product_packaging_usability/__init__.py
odoo/addons/product_packaging_usability/__manifest__.py
odoo/addons/product_packaging_usability/i18n/it.po
odoo/addons/product_packaging_usability/i18n/product_packaging_usability.pot
odoo/addons/product_packaging_usability/models/__init__.py
odoo/addons/product_packaging_usability/models/product_packaging.py
odoo/addons/product_packaging_usability/readme/CONTRIBUTORS.rst
odoo/addons/product_packaging_usability/readme/DESCRIPTION.rst
odoo/addons/product_packaging_usability/static/description/icon.png
odoo/addons/product_packaging_usability/static/description/im1.png
odoo/addons/product_packaging_usability/static/description/im2.png
odoo/addons/product_packaging_usability/static/description/im3.png
odoo/addons/product_packaging_usability/static/description/index.html
odoo/addons/product_packaging_usability/tests/__init__.py
odoo/addons/product_packaging_usability/tests/test_module.py
odoo/addons/product_packaging_usability/views/product_packaging.xml
odoo_addon_product_packaging_usability-16.0.1.0.1.2.dist-info/METADATA
odoo_addon_product_packaging_usability-16.0.1.0.1.2.dist-info/WHEEL
odoo_addon_product_packaging_usability-16.0.1.0.1.2.dist-info/top_level.txt
odoo_addon_product_packaging_usability-16.0.1.0.1.2.dist-info/RECORD
